{
  "query": "Design a high-performance thermoelectric material for waste heat recovery.\n\nRequirements:\n- High figure of merit (ZT > 1.5)\n- Operating temperature 600-800K\n- Use earth-abundant elements\n- Good thermal stability\n\nProvide 2-3 candidate compositions with energy and stability analysis.",
  "creative_mode": {
    "success": false,
    "result_length": 84,
    "result_preview": "'_GatheringFuture' object does not support the asynchronous context manager protocol"
  },
  "energy_focused_mode": {
    "success": false,
    "result_length": 84,
    "result_preview": "'_GatheringFuture' object does not support the asynchronous context manager protocol"
  }
}